logstack/__init__.py
logstack/decorators.py
logstack/handlers.py
logstack/loggers.py
logstack/serializers.py
logstack-0.0.7.dist-info/LICENSE
logstack-0.0.7.dist-info/METADATA
logstack-0.0.7.dist-info/WHEEL
logstack-0.0.7.dist-info/top_level.txt
logstack-0.0.7.dist-info/RECORD
