Metadata-Version: 2.1
Name: logstack
Version: 0.0.7
Summary: logstack is a convenience package to communicate with a logstack server
Home-page: https://github.com/strativ-dev/logstack
Author: LogStack Team
Author-email: prantoamt@gmail.com
License: UNKNOWN
Project-URL: Bug Tracker, https://github.com/strativ-dev/logstack/issues
Platform: UNKNOWN
Classifier: Programming Language :: Python :: 3.8
Classifier: License :: OSI Approved :: MIT License
Classifier: Operating System :: OS Independent
Requires-Python: >=3.8
License-File: LICENSE
Requires-Dist: boto3 (>=1.20.23)
Requires-Dist: certifi (>=2021.10.8)
Requires-Dist: charset-normalizer (>=2.0.11)
Requires-Dist: idna (>=3.3)
Requires-Dist: requests (>=2.27.1)
Requires-Dist: urllib3 (>=1.26.8)
